{
  "Properties": {
    "Translation": {
      "Name": "Races_Vanilla_BunnyBeanie"
    }
  },
  "CosmeticSlot": "HeadAccessory",
  "Appearance": {
    "Model": "Cosmetics/Head/BunnyBeanie.blockymodel",
    "TextureConfig": {
      "Type": "Gradient",
      "GradientSet": "Hair",
      "GrayscaleTexture": "Cosmetics/Head/BunnyBeanie_Textures/BunnyBeanie_Greyscale_Texture.png"
    }
  },
  "Icon": "Icons/Wardrobe/CosmeticsGenerated/BunnyBeanie.png",
  "IconProperties": {
    "Scale": 0.58823,
    "Rotation": [
      22.5,
      45,
      22.5
    ],
    "Translation": [
      0,
      -15
    ]
  }
}